[
  {
    "name": "Albania",
    "code": "AL",
    "emoji": "🇦🇱",
    "unicode": "U+1F1E6 U+1F1F1",
    "dial_code": "+355"
  },
  {
    "name": "Armenia",
    "code": "AM",
    "emoji": "🇦🇲",
    "unicode": "U+1F1E6 U+1F1F2",
    "dial_code": "+374"
  },
  {
    "name": "Australia",
    "code": "AU",
    "emoji": "🇦🇺",
    "unicode": "U+1F1E6 U+1F1FA",
    "dial_code": "+61"
  },
  {
    "name": "Austria",
    "code": "AT",
    "emoji": "🇦🇹",
    "unicode": "U+1F1E6 U+1F1F9",
    "dial_code": "+43"
  },
  {
    "name": "Azerbaijan",
    "code": "AZ",
    "emoji": "🇦🇿",
    "unicode": "U+1F1E6 U+1F1FF",
    "dial_code": "+994"
  },
  {
    "name": "Belarus",
    "code": "BY",
    "emoji": "🇧🇾",
    "unicode": "U+1F1E7 U+1F1FE",
    "dial_code": "+375"
  },
  {
    "name": "Belgium",
    "code": "BE",
    "emoji": "🇧🇪",
    "unicode": "U+1F1E7 U+1F1EA",
    "dial_code": "+32"
  },
  {
    "name": "Bosnia & Herzegovina",
    "code": "BA",
    "emoji": "🇧🇦",
    "unicode": "U+1F1E7 U+1F1E6",
    "dial_code": "+387"
  },
  {
    "name": "Brazil",
    "code": "BR",
    "emoji": "🇧🇷",
    "unicode": "U+1F1E7 U+1F1F7",
    "dial_code": "+55"
  },
  {
    "name": "Bulgaria",
    "code": "BG",
    "emoji": "🇧🇬",
    "unicode": "U+1F1E7 U+1F1EC",
    "dial_code": "+359"
  },
  {
    "name": "Canada",
    "code": "CA",
    "emoji": "🇨🇦",
    "unicode": "U+1F1E8 U+1F1E6",
    "dial_code": "+1"
  },
  {
    "name": "Chile",
    "code": "CL",
    "emoji": "🇨🇱",
    "unicode": "U+1F1E8 U+1F1F1",
    "dial_code": "+56"
  },
  {
    "name": "China",
    "code": "CN",
    "emoji": "🇨🇳",
    "unicode": "U+1F1E8 U+1F1F3",
    "dial_code": "+86"
  },
  {
    "name": "Croatia",
    "code": "HR",
    "emoji": "🇭🇷",
    "unicode": "U+1F1ED U+1F1F7",
    "dial_code": "+385"
  },
  {
    "name": "Cyprus",
    "code": "CY",
    "emoji": "🇨🇾",
    "unicode": "U+1F1E8 U+1F1FE",
    "dial_code": "+357"
  },
  {
    "name": "Czechia",
    "code": "CZ",
    "emoji": "🇨🇿",
    "unicode": "U+1F1E8 U+1F1FF",
    "dial_code": "+420"
  },
  {
    "name": "Denmark",
    "code": "DK",
    "emoji": "🇩🇰",
    "unicode": "U+1F1E9 U+1F1F0",
    "dial_code": "+45"
  },
  {
    "name": "Estonia",
    "code": "EE",
    "emoji": "🇪🇪",
    "unicode": "U+1F1EA U+1F1EA",
    "dial_code": "+372"
  },
  {
    "name": "Finland",
    "code": "FI",
    "emoji": "🇫🇮",
    "unicode": "U+1F1EB U+1F1EE",
    "dial_code": "+358"
  },
  {
    "name": "France",
    "code": "FR",
    "emoji": "🇫🇷",
    "unicode": "U+1F1EB U+1F1F7",
    "dial_code": "+33"
  },
  {
    "name": "Georgia",
    "code": "GE",
    "emoji": "🇬🇪",
    "unicode": "U+1F1EC U+1F1EA",
    "dial_code": "+995"
  },
  {
    "name": "Germany",
    "code": "DE",
    "emoji": "🇩🇪",
    "unicode": "U+1F1E9 U+1F1EA",
    "dial_code": "+49"
  },
  {
    "name": "Greece",
    "code": "GR",
    "emoji": "🇬🇷",
    "unicode": "U+1F1EC U+1F1F7",
    "dial_code": "+30"
  },
  {
    "name": "Hong Kong SAR China",
    "code": "HK",
    "emoji": "🇭🇰",
    "unicode": "U+1F1ED U+1F1F0",
    "dial_code": "+852"
  },
  {
    "name": "Hungary",
    "code": "HU",
    "emoji": "🇭🇺",
    "unicode": "U+1F1ED U+1F1FA",
    "dial_code": "+36"
  },
  {
    "name": "Iceland",
    "code": "IS",
    "emoji": "🇮🇸",
    "unicode": "U+1F1EE U+1F1F8",
    "dial_code": "+354"
  },
  {
    "name": "India",
    "code": "IN",
    "emoji": "🇮🇳",
    "unicode": "U+1F1EE U+1F1F3",
    "dial_code": "+91"
  },
  {
    "name": "Ireland",
    "code": "IE",
    "emoji": "🇮🇪",
    "unicode": "U+1F1EE U+1F1EA",
    "dial_code": "+353"
  },
  {
    "name": "Israel",
    "code": "IL",
    "emoji": "🇮🇱",
    "unicode": "U+1F1EE U+1F1F1",
    "dial_code": "+972"
  },
  {
    "name": "Italy",
    "code": "IT",
    "emoji": "🇮🇹",
    "unicode": "U+1F1EE U+1F1F9",
    "dial_code": "+39"
  },
  {
    "name": "Japan",
    "code": "JP",
    "emoji": "🇯🇵",
    "unicode": "U+1F1EF U+1F1F5",
    "dial_code": "+81"
  },
  {
    "name": "Kazakhstan",
    "code": "KZ",
    "emoji": "🇰🇿",
    "unicode": "U+1F1F0 U+1F1FF",
    "dial_code": "+7"
  },
  {
    "name": "Kosovo",
    "code": "XK",
    "emoji": "🇽🇰",
    "unicode": "U+1F1FD U+1F1F0",
    "dial_code": "+383"
  },
  {
    "name": "Kyrgyzstan",
    "code": "KG",
    "emoji": "🇰🇬",
    "unicode": "U+1F1F0 U+1F1EC",
    "dial_code": "+996"
  },
  {
    "name": "Latvia",
    "code": "LV",
    "emoji": "🇱🇻",
    "unicode": "U+1F1F1 U+1F1FB",
    "dial_code": "+371"
  },
  {
    "name": "Liechtenstein",
    "code": "LI",
    "emoji": "🇱🇮",
    "unicode": "U+1F1F1 U+1F1EE",
    "dial_code": "+423"
  },
  {
    "name": "Lithuania",
    "code": "LT",
    "emoji": "🇱🇹",
    "unicode": "U+1F1F1 U+1F1F9",
    "dial_code": "+370"
  },
  {
    "name": "Luxembourg",
    "code": "LU",
    "emoji": "🇱🇺",
    "unicode": "U+1F1F1 U+1F1FA",
    "dial_code": "+352"
  },
  {
    "name": "Macao SAR China",
    "code": "MO",
    "emoji": "🇲🇴",
    "unicode": "U+1F1F2 U+1F1F4",
    "dial_code": "+853"
  },
  {
    "name": "Malaysia",
    "code": "MY",
    "emoji": "🇲🇾",
    "unicode": "U+1F1F2 U+1F1FE",
    "dial_code": "+60"
  },
  {
    "name": "Malta",
    "code": "MT",
    "emoji": "🇲🇹",
    "unicode": "U+1F1F2 U+1F1F9",
    "dial_code": "+356"
  },
  {
    "name": "Mexico",
    "code": "MX",
    "emoji": "🇲🇽",
    "unicode": "U+1F1F2 U+1F1FD",
    "dial_code": "+52"
  },
  {
    "name": "Moldova",
    "code": "MD",
    "emoji": "🇲🇩",
    "unicode": "U+1F1F2 U+1F1E9",
    "dial_code": "+373"
  },
  {
    "name": "Monaco",
    "code": "MC",
    "emoji": "🇲🇨",
    "unicode": "U+1F1F2 U+1F1E8",
    "dial_code": "+377"
  },
  {
    "name": "Mongolia",
    "code": "MN",
    "emoji": "🇲🇳",
    "unicode": "U+1F1F2 U+1F1F3",
    "dial_code": "+976"
  },
  {
    "name": "Montenegro",
    "code": "ME",
    "emoji": "🇲🇪",
    "unicode": "U+1F1F2 U+1F1EA",
    "dial_code": "+382"
  },
  {
    "name": "Netherlands",
    "code": "NL",
    "emoji": "🇳🇱",
    "unicode": "U+1F1F3 U+1F1F1",
    "dial_code": "+31"
  },
  {
    "name": "New Zealand",
    "code": "NZ",
    "emoji": "🇳🇿",
    "unicode": "U+1F1F3 U+1F1FF",
    "dial_code": "+64"
  },
  {
    "name": "Norway",
    "code": "NO",
    "emoji": "🇳🇴",
    "unicode": "U+1F1F3 U+1F1F4",
    "dial_code": "+47"
  },
  {
    "name": "Pakistan",
    "code": "PK",
    "emoji": "🇵🇰",
    "unicode": "U+1F1F5 U+1F1F0",
    "dial_code": "+92"
  },
  {
    "name": "Peru",
    "code": "PE",
    "emoji": "🇵🇪",
    "unicode": "U+1F1F5 U+1F1EA",
    "dial_code": "+51"
  },
  {
    "name": "Philippines",
    "code": "PH",
    "emoji": "🇵🇭",
    "unicode": "U+1F1F5 U+1F1ED",
    "dial_code": "+63"
  },
  {
    "name": "Poland",
    "code": "PL",
    "emoji": "🇵🇱",
    "unicode": "U+1F1F5 U+1F1F1",
    "dial_code": "+48"
  },
  {
    "name": "Portugal",
    "code": "PT",
    "emoji": "🇵🇹",
    "unicode": "U+1F1F5 U+1F1F9",
    "dial_code": "+351"
  },
  {
    "name": "Qatar",
    "code": "QA",
    "emoji": "🇶🇦",
    "unicode": "U+1F1F6 U+1F1E6",
    "dial_code": "+974"
  },
  {
    "name": "Romania",
    "code": "RO",
    "emoji": "🇷🇴",
    "unicode": "U+1F1F7 U+1F1F4",
    "dial_code": "+40"
  },
  {
    "name": "Russia",
    "code": "RU",
    "emoji": "🇷🇺",
    "unicode": "U+1F1F7 U+1F1FA",
    "dial_code": "+7"
  },
  {
    "name": "Saudi Arabia",
    "code": "SA",
    "emoji": "🇸🇦",
    "unicode": "U+1F1F8 U+1F1E6",
    "dial_code": "+966"
  },
  {
    "name": "Serbia",
    "code": "RS",
    "emoji": "🇷🇸",
    "unicode": "U+1F1F7 U+1F1F8",
    "dial_code": "+381"
  },
  {
    "name": "Singapore",
    "code": "SG",
    "emoji": "🇸🇬",
    "unicode": "U+1F1F8 U+1F1EC",
    "dial_code": "+65"
  },
  {
    "name": "Slovakia",
    "code": "SK",
    "emoji": "🇸🇰",
    "unicode": "U+1F1F8 U+1F1F0",
    "dial_code": "+421"
  },
  {
    "name": "Slovenia",
    "code": "SI",
    "emoji": "🇸🇮",
    "unicode": "U+1F1F8 U+1F1EE",
    "dial_code": "+386"
  },
  {
    "name": "South Korea",
    "code": "KR",
    "emoji": "🇰🇷",
    "unicode": "U+1F1F0 U+1F1F7",
    "dial_code": "+82"
  },
  {
    "name": "Spain",
    "code": "ES",
    "emoji": "🇪🇸",
    "unicode": "U+1F1EA U+1F1F8",
    "dial_code": "+34"
  },
  {
    "name": "Sweden",
    "code": "SE",
    "emoji": "🇸🇪",
    "unicode": "U+1F1F8 U+1F1EA",
    "dial_code": "+46"
  },
  {
    "name": "Switzerland",
    "code": "CH",
    "emoji": "🇨🇭",
    "unicode": "U+1F1E8 U+1F1ED",
    "dial_code": "+41"
  },
  {
    "name": "Taiwan",
    "code": "TW",
    "emoji": "🇹🇼",
    "unicode": "U+1F1F9 U+1F1FC",
    "dial_code": "+886"
  },
  {
    "name": "Tajikistan",
    "code": "TJ",
    "emoji": "🇹🇯",
    "unicode": "U+1F1F9 U+1F1EF",
    "dial_code": "+992"
  },
  {
    "name": "Thailand",
    "code": "TH",
    "emoji": "🇹🇭",
    "unicode": "U+1F1F9 U+1F1ED",
    "dial_code": "+66"
  },
  {
    "name": "Turkey",
    "code": "TR",
    "emoji": "🇹🇷",
    "unicode": "U+1F1F9 U+1F1F7",
    "dial_code": "+90"
  },
  {
    "name": "Turkmenistan",
    "code": "TM",
    "emoji": "🇹🇲",
    "unicode": "U+1F1F9 U+1F1F2",
    "dial_code": "+993"
  },
  {
    "name": "Ukraine",
    "code": "UA",
    "emoji": "🇺🇦",
    "unicode": "U+1F1FA U+1F1E6",
    "dial_code": "+380"
  },
  {
    "name": "United Arab Emirates",
    "code": "AE",
    "emoji": "🇦🇪",
    "unicode": "U+1F1E6 U+1F1EA",
    "dial_code": "+971"
  },
  {
    "name": "United Kingdom",
    "code": "GB",
    "emoji": "🇬🇧",
    "unicode": "U+1F1EC U+1F1E7",
    "dial_code": "+44"
  },
  {
    "name": "United States",
    "code": "US",
    "emoji": "🇺🇸",
    "unicode": "U+1F1FA U+1F1F8",
    "dial_code": "+1"
  },
  {
    "name": "Uzbekistan",
    "code": "UZ",
    "emoji": "🇺🇿",
    "unicode": "U+1F1FA U+1F1FF",
    "dial_code": "+998"
  },
  {
    "name": "Vatican City",
    "code": "VA",
    "emoji": "🇻🇦",
    "unicode": "U+1F1FB U+1F1E6",
    "dial_code": "+379"
  },
  {
    "name": "Venezuela",
    "code": "VE",
    "emoji": "🇻🇪",
    "unicode": "U+1F1FB U+1F1EA",
    "dial_code": "+58"
  },
  {
    "name": "Vietnam",
    "code": "VN",
    "emoji": "🇻🇳",
    "unicode": "U+1F1FB U+1F1F3",
    "dial_code": "+84"
  }
]
